daterange/__init__.py
daterange/apps.py
daterange/filters.py
daterange/forms.py
daterange/locale/en/LC_MESSAGES/django.mo
daterange/locale/en/LC_MESSAGES/django.po
daterange/static/css/admin/daterange.css
daterange/static/js/admin/DateRangeShortcuts.js
daterange/templates/admin/daterange/change_list.html
daterange/templates/admin/daterange/filter_form.html
django_daterange_filterspec-2.0.5.dist-info/LICENSE.txt
django_daterange_filterspec-2.0.5.dist-info/METADATA
django_daterange_filterspec-2.0.5.dist-info/WHEEL
django_daterange_filterspec-2.0.5.dist-info/top_level.txt
django_daterange_filterspec-2.0.5.dist-info/RECORD
