Metadata-Version: 2.1
Name: django-daterange-filterspec
Version: 2.0.5
Summary: A DateRange Filter for Django Admin Changelists
Author: Stuart MacKay
Author-email: smackay@flagstonesoftware.com
License: License :: OSI Approved :: BSD License
Keywords: Django Admin DateRage Filter Changelists
Classifier: Development Status :: 3 - Alpha
Classifier: Framework :: Django :: 2.2
Classifier: Framework :: Django :: 3.0
Classifier: Framework :: Django :: 3.2
Classifier: Framework :: Django :: 4.0
Classifier: Intended Audience :: Developers
Classifier: License :: OSI Approved :: BSD License
Classifier: Natural Language :: English
Classifier: Programming Language :: Python
Classifier: Programming Language :: Python :: 3
Classifier: Programming Language :: Python :: 3.8
Classifier: Programming Language :: Python :: 3.9
Classifier: Programming Language :: Python :: 3.10
Requires-Python: >=3.7
License-File: LICENSE.txt
Requires-Dist: Django >=2.2
